strapi_api_sdk/__init__.py
strapi_api_sdk/models/__init__.py
strapi_api_sdk/models/exceptions.py
strapi_api_sdk/sdk/__init__.py
strapi_api_sdk/sdk/client.py
strapi_api_sdk/sdk/modules/__init__.py
strapi_api_sdk/sdk/modules/auth.py
strapi_api_sdk/sdk/modules/http.py
strapi_api_sdk/sdk/modules/user.py
strapi_api_sdk/utils/__init__.py
strapi_api_sdk/utils/constants.py
strapi_api_sdk/utils/http_utils.py
strapi_api_sdk-0.2.1.dist-info/LICENSE
strapi_api_sdk-0.2.1.dist-info/METADATA
strapi_api_sdk-0.2.1.dist-info/WHEEL
strapi_api_sdk-0.2.1.dist-info/RECORD
