Metadata-Version: 2.1
Name: strapi-api-sdk
Version: 0.2.1
Summary: Interact with Strapi functionalities within your python application, includes the ability to perform create, read, update, and delete (CRUD) operations on existing APIs endpoints and provides an Authenticator class ready to create new users, API Tokens and etc.
License: MIT
Author: rapha-pereira
Author-email: raphaelpgomes1@gmail.com
Requires-Python: >=3.9,<4.0
Classifier: License :: OSI Approved :: MIT License
Classifier: Programming Language :: Python :: 3
Classifier: Programming Language :: Python :: 3.9
Classifier: Programming Language :: Python :: 3.10
Classifier: Programming Language :: Python :: 3.11
Requires-Dist: python-decouple (>=3.8,<4.0)
Requires-Dist: requests (>=2.31.0,<3.0.0)
